pleaserender/__init__.py
pleaserender/util.py
pleaserender/core/__init__.py
pleaserender/core/figure.py
pleaserender/core/plot.py
pleaserender/core/plot_object.py
pleaserender/core/render_state.py
pleaserender/core/scatter.py
pleaserender/exoplanet/__init__.py
pleaserender/exoplanet/bandpass.py
pleaserender/exoplanet/image.py
pleaserender/exoplanet/observation.py
pleaserender/exoplanet/observation_frames.py
pleaserender/exoplanet/orbit.py
pleaserender/exoplanet/spectral_cube.py
pleaserender-1.0.1.dist-info/METADATA
pleaserender-1.0.1.dist-info/WHEEL
pleaserender-1.0.1.dist-info/licenses/LICENSE
pleaserender-1.0.1.dist-info/RECORD
