Metadata-Version: 2.3
Name: pleaserender
Version: 1.0.1
Summary: The polite exoplanet rendering library
Project-URL: Homepage, https://github.com/CoreySpohn/pleaserender
Project-URL: Issues, https://github.com/CoreySpohn/pleaserender/issues
Author-email: Corey Spohn <corey.a.spohn@nasa.gov>
License: MIT License
License-File: LICENSE
Classifier: Development Status :: 3 - Alpha
Classifier: Intended Audience :: Science/Research
Classifier: License :: OSI Approved :: MIT License
Classifier: Programming Language :: Python :: 3
Classifier: Topic :: Scientific/Engineering :: Astronomy
Requires-Dist: astropy
Requires-Dist: matplotlib
Requires-Dist: numpy
Requires-Dist: xarray
